GEMA/__init__.py
GEMA/classification.py
GEMA/iterativesom.py
GEMA/map.py
GEMA/visualization.py
GEMA-0.4.2.dist-info/LICENSE
GEMA-0.4.2.dist-info/METADATA
GEMA-0.4.2.dist-info/WHEEL
GEMA-0.4.2.dist-info/top_level.txt
GEMA-0.4.2.dist-info/RECORD
