Metadata-Version: 2.1
Name: GEMA
Version: 0.4.2
Summary: A library to build and study Self-Organizing-Maps
Home-page: https://github.com/ufvceiec/GEMA
Author: UFV CEIEC
Author-email: ceiec.info@ceiec.es
License: UNKNOWN
Platform: UNKNOWN
Classifier: Programming Language :: Python :: 3
Classifier: Operating System :: OS Independent
